cometspy/__init__.py
cometspy/comets.py
cometspy/layout.py
cometspy/model.py
cometspy/params.py
cometspy/utils.py
cometspy-0.6.2.dist-info/METADATA
cometspy-0.6.2.dist-info/WHEEL
cometspy-0.6.2.dist-info/top_level.txt
cometspy-0.6.2.dist-info/RECORD
