Metadata-Version: 2.4
Name: cometspy
Version: 0.6.2
Summary: The Python interface to COMETS
Author-email: The COMETSPy Core Team <dukovski@bu.edu>
License:                     GNU GENERAL PUBLIC LICENSE
Project-URL: Homepage, https://github.com/segrelab/cometspy
Keywords: metabolism,dynamic,flux,balance,analysis,spatial,evolution
Classifier: Development Status :: 4 - Beta
Classifier: Intended Audience :: Science/Research
Classifier: License :: OSI Approved :: GNU General Public License v3 (GPLv3)
Classifier: Programming Language :: Python :: 3.6
Classifier: Programming Language :: Python :: 3.7
Classifier: Programming Language :: Python :: 3.8
Requires-Python: >=3.6
Requires-Dist: numpy
Requires-Dist: cobra
Requires-Dist: pandas>=1.0.0
Requires-Dist: tqdm
